biothings_explorer/__init__.py
biothings_explorer/_deprecated_mapping_parser.py
biothings_explorer/_deprecated_registry.py
biothings_explorer/_deprecated_schema_parser.py
biothings_explorer/api_call_dispatcher.py
biothings_explorer/api_output_parser.py
biothings_explorer/apicall.py
biothings_explorer/config.py
biothings_explorer/config_new.py
biothings_explorer/hint.py
biothings_explorer/id_resolver.py
biothings_explorer/json_transformer.py
biothings_explorer/metadata.py
biothings_explorer/registry.py
biothings_explorer/smartapi_parser.py
biothings_explorer/user_query_dispatcher.py
biothings_explorer/write_graphml.py
biothings_explorer/api_preprocess/__init__.py
biothings_explorer/api_preprocess/biolink.py
biothings_explorer/api_preprocess/cord.py
biothings_explorer/api_preprocess/ctd.py
biothings_explorer/api_preprocess/opentarget.py
biothings_explorer/api_preprocess/reasoner.py
biothings_explorer/api_preprocess/scibite.py
biothings_explorer/api_preprocess/semmed.py
biothings_explorer/api_preprocess/stanford.py
biothings_explorer/call_apis/__init__.py
biothings_explorer/call_apis/filter.py
biothings_explorer/call_apis/query_builder.py
biothings_explorer/call_apis/api_response_transform/__init__.py
biothings_explorer/call_apis/api_response_transform/transformers/__init__.py
biothings_explorer/call_apis/api_response_transform/transformers/automat_transformer.py
biothings_explorer/call_apis/api_response_transform/transformers/base_transformer.py
biothings_explorer/call_apis/api_response_transform/transformers/biolink_transformer.py
biothings_explorer/call_apis/api_response_transform/transformers/biothings_transformer.py
biothings_explorer/call_apis/api_response_transform/transformers/cohd_transformer.py
biothings_explorer/call_apis/api_response_transform/transformers/cord_transformer.py
biothings_explorer/call_apis/api_response_transform/transformers/ctd_transformer.py
biothings_explorer/call_apis/api_response_transform/transformers/diseases_transformer.py
biothings_explorer-1.1.0.dist-info/LICENSE
biothings_explorer-1.1.0.dist-info/METADATA
biothings_explorer-1.1.0.dist-info/WHEEL
biothings_explorer-1.1.0.dist-info/dependency_links.txt
biothings_explorer-1.1.0.dist-info/top_level.txt
biothings_explorer-1.1.0.dist-info/RECORD
